postgresql_audit/__init__.py
postgresql_audit/base.py
postgresql_audit/expressions.py
postgresql_audit/flask.py
postgresql_audit/migrations.py
postgresql_audit/templates/audit_table_row_level.sql
postgresql_audit/templates/audit_table_stmt_level.sql
postgresql_audit/templates/create_activity_row_level.sql
postgresql_audit/templates/create_activity_stmt_level.sql
postgresql_audit/templates/create_schema.sql
postgresql_audit/templates/drop_schema.sql
postgresql_audit/templates/jsonb_change_key_name.sql
postgresql_audit/templates/operators.sql
postgresql_audit-0.17.1.dist-info/METADATA
postgresql_audit-0.17.1.dist-info/WHEEL
postgresql_audit-0.17.1.dist-info/licenses/LICENSE
postgresql_audit-0.17.1.dist-info/RECORD
