Metadata-Version: 2.1
Name: postgresql-audit
Version: 0.17.1
Summary: Versioning and auditing extension for PostgreSQL and SQLAlchemy.
Project-URL: Homepage, https://github.com/kvesteri/postgresql-audit
Author-email: Konsta Vesterinen <konsta@fastmonkeys.com>
License-Expression: BSD-2-Clause
License-File: LICENSE
Classifier: Environment :: Web Environment
Classifier: Intended Audience :: Developers
Classifier: License :: OSI Approved :: BSD License
Classifier: Operating System :: OS Independent
Classifier: Programming Language :: Python
Classifier: Programming Language :: Python :: 3
Classifier: Programming Language :: Python :: 3.8
Classifier: Programming Language :: Python :: 3.9
Classifier: Programming Language :: Python :: 3.10
Classifier: Programming Language :: Python :: 3.11
Classifier: Topic :: Internet :: WWW/HTTP :: Dynamic Content
Classifier: Topic :: Software Development :: Libraries :: Python Modules
Requires-Python: >=3.8
Requires-Dist: sqlalchemy-utils>=0.37.0
Requires-Dist: sqlalchemy>=1.4
